.gitignore
.hgignore
.hgtags
HACKING.txt
HISTORY.txt
HISTORY.txt.orig
MANIFEST.in
README.rst
bootstrap.py
buildout.cfg
setup.py
setup.py.orig
src/trac2rst/__init__.py
src/trac2rst/core.py
src/trac2rst.egg-info/PKG-INFO
src/trac2rst.egg-info/SOURCES.txt
src/trac2rst.egg-info/dependency_links.txt
src/trac2rst.egg-info/entry_points.txt
src/trac2rst.egg-info/not-zip-safe
src/trac2rst.egg-info/top_level.txt
src/trac2rst/tests/wikitext.txt