Metadata-Version: 1.0
Name: trac2rst
Version: 0.2
Summary: Quick an dirty tool to transform text in Trac Wiki formatting to Restructured Text
Home-page: https://bitbucket.org/pcaro/trac2rest
Author: Yaco Sistemas
Author-email: pcaro@yaco.es
License: MIT
Keywords: restructuredtext,rst,converter
Platform: UNKNOWN
Classifier: License :: OSI Approved :: MIT License
Classifier: Programming Language :: Python
Classifier: Topic :: Documentation
Classifier: Topic :: Software Development :: Documentation
Classifier: Framework :: Trac
Classifier: Topic :: Text Processing
Classifier: Topic :: Utilities
